crowdstrike/foundry/function/__init__.py
crowdstrike/foundry/function/config_loader.py
crowdstrike/foundry/function/config_loader_fs.py
crowdstrike/foundry/function/context.py
crowdstrike/foundry/function/loader.py
crowdstrike/foundry/function/mapping.py
crowdstrike/foundry/function/model.py
crowdstrike/foundry/function/router.py
crowdstrike/foundry/function/runner.py
crowdstrike/foundry/function/runner_cli.py
crowdstrike/foundry/function/runner_http.py
crowdstrike_foundry_function-1.1.3.data/data/requirements.txt
crowdstrike_foundry_function-1.1.3.dist-info/licenses/LICENSE
crowdstrike_foundry_function-1.1.3.dist-info/METADATA
crowdstrike_foundry_function-1.1.3.dist-info/WHEEL
crowdstrike_foundry_function-1.1.3.dist-info/top_level.txt
crowdstrike_foundry_function-1.1.3.dist-info/RECORD
