Metadata-Version: 2.4
Name: crowdstrike-foundry-function
Version: 1.1.3
Summary: CrowdStrike Foundry Function Software Developer Kit for Python
Author-email: CrowdStrike <foundry-fn-python@crowdstrike.com>
Maintainer-email: John Stone <foundry-fn-python@crowdstrike.com>, Chris Cannon <foundry-fn-python@crowdstrike.com>, Johnny Steenbergen <foundry-fn-python@crowdstrike.com>, Banu Yuceer <foundry-fn-python@crowdstrike.com>, Joshua Hiller <foundry-fn-python@crowdstrike.com>
Project-URL: Homepage, https://github.com/CrowdStrike/foundry-fn-python
Project-URL: Tracker, https://github.com/CrowdStrike/foundry-fn-python/issues
Keywords: crowdstrike,crowdstrike-falcon-foundry,foundry,foundry-functions,crowdstrike-faas,sdk
Classifier: Development Status :: 5 - Production/Stable
Classifier: Framework :: Flake8
Classifier: Intended Audience :: Developers
Classifier: License :: OSI Approved :: The Unlicense (Unlicense)
Classifier: Natural Language :: English
Classifier: Operating System :: MacOS
Classifier: Operating System :: Microsoft :: Windows
Classifier: Operating System :: OS Independent
Classifier: Operating System :: POSIX
Classifier: Operating System :: POSIX :: Linux
Classifier: Operating System :: Unix
Classifier: Programming Language :: Python
Classifier: Programming Language :: Python :: 3
Classifier: Programming Language :: Python :: 3.9
Classifier: Programming Language :: Python :: 3.10
Classifier: Programming Language :: Python :: 3.11
Classifier: Programming Language :: Python :: 3.12
Classifier: Programming Language :: Python :: 3.13
Classifier: Topic :: Security
Classifier: Topic :: Software Development :: Libraries :: Python Modules
Classifier: Topic :: System :: Systems Administration
Classifier: Topic :: Utilities
Requires-Python: >=3.9.0
License-File: LICENSE
Requires-Dist: build>=1.0.3
Requires-Dist: pytest>=9.0.2
Requires-Dist: python-multipart>=0.0.20
Requires-Dist: urllib3>=2.6.1
Dynamic: license-file
Dynamic: requires-dist
Dynamic: requires-python
